odoo/addons/l10n_ru_banks/README.rst
odoo/addons/l10n_ru_banks/__init__.py
odoo/addons/l10n_ru_banks/__manifest__.py
odoo/addons/l10n_ru_banks/data/res_bank_demo.xml
odoo/addons/l10n_ru_banks/i18n/l10n_ru_banks.pot
odoo/addons/l10n_ru_banks/i18n/ru.po
odoo/addons/l10n_ru_banks/models/__init__.py
odoo/addons/l10n_ru_banks/models/res_bank.py
odoo/addons/l10n_ru_banks/readme/CONTRIBUTORS.md
odoo/addons/l10n_ru_banks/readme/DESCRIPTION.md
odoo/addons/l10n_ru_banks/security/ir.model.access.csv
odoo/addons/l10n_ru_banks/static/description/icon.png
odoo/addons/l10n_ru_banks/static/description/index.html
odoo/addons/l10n_ru_banks/views/res_bank.xml
odoo/addons/l10n_ru_banks/wizard/__init__.py
odoo/addons/l10n_ru_banks/wizard/update_banks_wizard.py
odoo_addon_l10n_ru_banks-17.0.1.0.0.6.dist-info/METADATA
odoo_addon_l10n_ru_banks-17.0.1.0.0.6.dist-info/WHEEL
odoo_addon_l10n_ru_banks-17.0.1.0.0.6.dist-info/top_level.txt
odoo_addon_l10n_ru_banks-17.0.1.0.0.6.dist-info/RECORD
